[
    {
        "name": "Laptop",
        "quantity": 20
    },
    {
        "name": "Keyboard",
        "quantity": 15
    },
    {
        "name": "Monitor",
        "quantity": 20
    },
    {
        "name": "CPU",
        "quantity": 25
    },
    {
        "name": "GPU",
        "quantity": 30
    },
    {
        "name": "Memory",
        "quantity": 21
    },
    {
        "name": "HDD",
        "quantity": 40
    },
    {
        "name": "SSD",
        "quantity": 72
    },
    {
        "name": "Speaker",
        "quantity": 68
    }
]